pycratch/__about__.py
pycratch/__init__.py
pycratch-0.0.1.dist-info/METADATA
pycratch-0.0.1.dist-info/WHEEL
pycratch-0.0.1.dist-info/licenses/LICENSE.txt
pycratch-0.0.1.dist-info/RECORD
